{
  "type": "restapi",
  "host": null,
  "port": null,
  "databaseName": null,
  "databaseUsername": null,
  "description": null,
  "outboundRegion": null,
  "ssl": null,
  "editPrivilege": null,
  "options": {
    "auth0_clientID": "",
    "auth0_custom_audience": "",
    "auth0_domain": "",
    "authentication": "",
    "baseURL": "https://infx-internal.prod.projectronin.io/",
    "basic_username": "",
    "cookiesToForward": [],
    "extraBodyKeyValues": [["", ""]],
    "forwardAllCookies": false,
    "headers": [["", ""]],
    "oauth1_signature_method": "HMAC-SHA1",
    "oauth2_access_token_url": "",
    "oauth2_auth_url": "",
    "oauth2_callback_url": "OAUTH2_CALLBACK_URL",
    "oauth2_client_id": "",
    "oauth2_scope": "",
    "session_cookie_name": "",
    "urlparams": [["", ""]],
    "verify_session_url": ""
  },
  "environment": "production",
  "dynamicallyQueryable": false,
  "uuid": "a00335cd-bd3b-4d98-8af4-7ff590ce95e8",
  "toolscriptVersion": "1.0.0"
}
